opennpi/__init__.py
opennpi/openNPI.py
opennpi_scraper-0.1.1.dist-info/LICENSE
opennpi_scraper-0.1.1.dist-info/METADATA
opennpi_scraper-0.1.1.dist-info/WHEEL
opennpi_scraper-0.1.1.dist-info/top_level.txt
opennpi_scraper-0.1.1.dist-info/RECORD
