Metadata-Version: 2.1
Name: opennpi-scraper
Version: 0.1.1
Summary: The `opennpi-scraper` is designed for seamless interaction with the opennpi.com page
Home-page: https://github.com/Diego-Arrechea/opennpi-scraper
Author: Diego Arrechea
Author-email: diego.arrechea.job@gmail.com
License: MIT
Requires-Python: >=3.6
License-File: LICENSE
Requires-Dist: requests
Requires-Dist: beautifulsoup4
